LICENSE
MANIFEST.in
README.md
setup.py
PTTOTP/PTTOTP.py
PTTOTP/Version.py
PTTOTP.egg-info/PKG-INFO
PTTOTP.egg-info/SOURCES.txt
PTTOTP.egg-info/dependency_links.txt
PTTOTP.egg-info/requires.txt
PTTOTP.egg-info/top_level.txt
PTTOTP/Res/qrious.js