Metadata-Version: 1.2
Name: PTTOTP
Version: 0.0.1.dev
Summary: PTT OTP
Home-page: UNKNOWN
Author: CodingMan
Author-email: thetruth0906@gmail.com
License: UNKNOWN
Keywords: PTT,OTP,One Time Password
Platform: UNKNOWN
Classifier: Development Status :: 4 - Beta
Classifier: Intended Audience :: Developers
Classifier: Topic :: Communications :: BBS
Classifier: Topic :: Software Development :: Libraries :: Python Modules
Classifier: Topic :: Internet
Classifier: License :: OSI Approved :: MIT License
Classifier: Programming Language :: Python :: 3
Classifier: Programming Language :: Python :: 3.4
Classifier: Programming Language :: Python :: 3.5
Classifier: Programming Language :: Python :: 3.6
Requires-Python: >=3
